tinykv/__init__.py
tinykv/py.typed
tinykv-0.1.2.dist-info/licenses/LICENSE
tinykv-0.1.2.dist-info/WHEEL
tinykv-0.1.2.dist-info/METADATA
tinykv-0.1.2.dist-info/RECORD
